fluid_domain/__init__.py
fluid_domain/art.py
KMEngine-1.1.2.dist-info/LICENSE.txt
KMEngine-1.1.2.dist-info/METADATA
KMEngine-1.1.2.dist-info/WHEEL
KMEngine-1.1.2.dist-info/top_level.txt
KMEngine-1.1.2.dist-info/RECORD
