Metadata-Version: 2.1
Name: KMEngine
Version: 1.1.2
Summary: This package streamlines machine learning model training, evaluation, and customization with support for regression and classification tasks, automated workflow, diverse model integration, EDA, serialization, and parameter tuning.
Home-page: https://github.com/KarthikDevalla/Karthiks_Model_Engine.git
Author: Karthik Devalla
Author-email: ihatecoding666@gmail.com
Classifier: Programming Language :: Python :: 3
Classifier: License :: OSI Approved :: MIT License
Classifier: Operating System :: OS Independent
Requires-Python: >=3.10
License-File: LICENSE.txt
